discodos/__init__.py
discodos/args_helper.py
discodos/config.py
discodos/log.py
discodos/utils.py
discodos/cmd/__init__.py
discodos/cmd/sync.py
discodos/cmd23/__init__.py
discodos/cmd23/clean.py
discodos/cmd23/helper.py
discodos/cmd23/import_.py
discodos/cmd23/links.py
discodos/cmd23/ls.py
discodos/cmd23/mix.py
discodos/cmd23/search.py
discodos/cmd23/sell.py
discodos/cmd23/setup.py
discodos/cmd23/stats.py
discodos/cmd23/suggest.py
discodos/ctrl/__init__.py
discodos/ctrl/collection.py
discodos/ctrl/common.py
discodos/ctrl/mix.py
discodos/ctrl/tui.py
discodos/ctrl/tui_edit.py
discodos/ctrl/tui_folder.py
discodos/ctrl/tui_ls.tcss
discodos/model/__init__.py
discodos/model/brainz.py
discodos/model/brainz_match.py
discodos/model/collection.py
discodos/model/database.py
discodos/model/discogs.py
discodos/model/mix.py
discodos/view/__init__.py
discodos/view/collection.py
discodos/view/common.py
discodos/view/mix.py
discodos-3.2.1.dist-info/licenses/LICENSE.txt
tests/__init__.py
tests/test_brainz.py
tests/test_collection.py
tests/test_config.py
tests/test_mix.py
discodos-3.2.1.dist-info/METADATA
discodos-3.2.1.dist-info/WHEEL
discodos-3.2.1.dist-info/entry_points.txt
discodos-3.2.1.dist-info/top_level.txt
discodos-3.2.1.dist-info/RECORD
