Metadata-Version: 2.4
Name: discodos
Version: 3.2.1
Summary: DJ and record collector's toolbox for Discogs
Home-page: https://discodos.jojotodos.net
Author: J0J0 Todos
License: GPLv3+
Project-URL: Bug Tracker, https://github.com/joj0/discodos/issues
Project-URL: Documentation, https://discodos.readthedocs.io
Project-URL: Source Code, https://github.com/joj0/discodos/
Classifier: License :: OSI Approved :: GNU General Public License v3 or later (GPLv3+)
Classifier: Programming Language :: Python :: 3
Classifier: Programming Language :: Python :: 3.9
Classifier: Programming Language :: Python :: 3.10
Classifier: Programming Language :: Python :: 3.11
Classifier: Programming Language :: Python :: 3.12
Classifier: Topic :: Multimedia :: Sound/Audio
Classifier: Environment :: Console
License-File: LICENSE.txt
Requires-Dist: Click
Requires-Dist: tabulate
Requires-Dist: PyYaml
Requires-Dist: click-option-group
Requires-Dist: dropbox
Requires-Dist: musicbrainzngs
Requires-Dist: rich
Requires-Dist: textual
Requires-Dist: python3-discogs-client>=2.8
Requires-Dist: webdavclient3
Dynamic: author
Dynamic: classifier
Dynamic: description
Dynamic: description-content-type
Dynamic: home-page
Dynamic: license
Dynamic: license-file
Dynamic: project-url
Dynamic: requires-dist
Dynamic: summary
